setup.py
pete_game_test/AnimalClass.py
pete_game_test/CharacterClass.py
pete_game_test/GameClass.py
pete_game_test/__init__.py
pete_game_test1.egg-info/PKG-INFO
pete_game_test1.egg-info/SOURCES.txt
pete_game_test1.egg-info/dependency_links.txt
pete_game_test1.egg-info/not-zip-safe
pete_game_test1.egg-info/top_level.txt