Metadata-Version: 1.0
Name: pete-game-test1
Version: 0.2
Summary: test pete game upload
Home-page: UNKNOWN
Author: Pete Tae
Author-email: UNKNOWN
License: UNKNOWN
Platform: UNKNOWN
